rios.conversion-0.6.2-py3.8-nspkg.pth
rios/conversion/__init__.py
rios/conversion/exception.py
rios/conversion/base/__init__.py
rios/conversion/base/base.py
rios/conversion/base/from_rios.py
rios/conversion/base/structures.py
rios/conversion/base/to_rios.py
rios/conversion/qualtrics/__init__.py
rios/conversion/qualtrics/from_rios.py
rios/conversion/qualtrics/to_rios.py
rios/conversion/redcap/__init__.py
rios/conversion/redcap/from_rios.py
rios/conversion/redcap/functions.py
rios/conversion/redcap/to_rios.py
rios/conversion/utils/__init__.py
rios/conversion/utils/balanced_match.py
rios/conversion/utils/csv_reader.py
rios/conversion/utils/instrument_calc_storage.py
rios/conversion/utils/json_reader.py
rios/conversion/utils/log.py
rios.conversion-0.6.2.dist-info/LICENSE.rst
rios.conversion-0.6.2.dist-info/METADATA
rios.conversion-0.6.2.dist-info/NOTICE
rios.conversion-0.6.2.dist-info/WHEEL
rios.conversion-0.6.2.dist-info/namespace_packages.txt
rios.conversion-0.6.2.dist-info/top_level.txt
rios.conversion-0.6.2.dist-info/zip-safe
rios.conversion-0.6.2.dist-info/RECORD
