Metadata-Version: 2.1
Name: rios.conversion
Version: 0.6.2
Summary: Module for converting Instruments to and from RIOS
Home-page: https://github.com/prometheusresearch/rios.conversion
Author: Prometheus Research, LLC
Author-email: contact@prometheusresearch.com
License: Apache-2.0
Keywords: rios instrument assessment conversion
Platform: UNKNOWN
Classifier: Intended Audience :: Developers
Classifier: License :: OSI Approved :: Apache Software License
Classifier: Programming Language :: Python :: 2.7
Classifier: Programming Language :: Python :: 3.5
Classifier: Programming Language :: Python :: 3.6
Classifier: Programming Language :: Python :: 3.7
Classifier: Programming Language :: Python :: 3.8
Requires-Dist: pyyaml
Requires-Dist: rios.core (<1,>=0.6.0)
Requires-Dist: simplejson (==3.8.2)
